audio_image_embedder/__init__.py
audio_image_embedder/embedder.py
audio_image_embedder-0.1.0.dist-info/METADATA
audio_image_embedder-0.1.0.dist-info/WHEEL
audio_image_embedder-0.1.0.dist-info/top_level.txt
audio_image_embedder-0.1.0.dist-info/RECORD
